MANIFEST.in
README.md
requirements.txt
setup.py
dirmaker/__init__.py
dirmaker/dirmaker.py
dirmaker.egg-info/PKG-INFO
dirmaker.egg-info/SOURCES.txt
dirmaker.egg-info/dependency_links.txt
dirmaker.egg-info/entry_points.txt
dirmaker.egg-info/requires.txt
dirmaker.egg-info/top_level.txt
dirmaker/example/config.yml
dirmaker/example/data.yml
dirmaker/example/template.html
dirmaker/example/static/logo.svg
dirmaker/example/static/main.js
dirmaker/example/static/style.css
dirmaker/example/static/thumb.png