Metadata-Version: 2.1
Name: dirmaker
Version: 1.0.1
Summary: A simple static site generator for generating directory websites.
Home-page: https://github.com/knadh/dirmaker
Author: Kailash Nadh
Author-email: kailash@nadh.in
License: MIT License
Download-URL: https://github.com/knadh/dirmaker
Platform: UNKNOWN
Classifier: Topic :: Text Editors :: Text Processing
Classifier: Topic :: Internet :: WWW/HTTP :: Site Management
Classifier: Topic :: Documentation
